pyControl4/__init__.py
pyControl4/account.py
pyControl4/alarm.py
pyControl4/blind.py
pyControl4/director.py
pyControl4/error_handling.py
pyControl4/light.py
pyControl4/relay.py
pyControl4/room.py
pyControl4/websocket.py
pyC4API-1.0.1.dist-info/LICENSE
pyC4API-1.0.1.dist-info/METADATA
pyC4API-1.0.1.dist-info/WHEEL
pyC4API-1.0.1.dist-info/top_level.txt
pyC4API-1.0.1.dist-info/RECORD
