Metadata-Version: 2.1
Name: pyC4API
Version: 1.0.1
Summary: Forked Python 3 asyncio package for interacting with Control4 systems and includes room support
Home-page: https://github.com/nalin29/pyControl4.git
Author: nalin29
Author-email: github@nalinmahajan.com
Classifier: Programming Language :: Python :: 3
Classifier: License :: OSI Approved :: Apache Software License
Classifier: Operating System :: OS Independent
Requires-Python: >=3.6
License-File: LICENSE
Requires-Dist: aiohttp
Requires-Dist: xmltodict
Requires-Dist: python-socketio (<5,>=4)
Requires-Dist: websocket-client
